s3_zipper/__initi__.py
s3_zipper/cli.py
s3_zipper/logger.py
s3_zipper/progress.py
s3_zipper/s3_client.py
s3_zipper/unzip_flow.py
s3_zipper/utils.py
s3_zipper/zip_flow.py
s3_zipper-0.1.0.dist-info/METADATA
s3_zipper-0.1.0.dist-info/WHEEL
s3_zipper-0.1.0.dist-info/entry_points.txt
s3_zipper-0.1.0.dist-info/RECORD
