Metadata-Version: 2.4
Name: s3_zipper
Version: 0.1.0
Summary: Fast ZIP/UNZIP utility for S3 with same-account and cross-account support.
Author-email: Nasrul <hasanali242424@gmail.com>
Requires-Python: >=3.9
Requires-Dist: boto3>=1.20
Requires-Dist: zipstream>=1.1.4
